pytwin/__init__.py
pytwin/decorators.py
pytwin/evaluate/__init__.py
pytwin/evaluate/model.py
pytwin/evaluate/saved_state_registry.py
pytwin/evaluate/tbrom.py
pytwin/evaluate/twin_model.py
pytwin/examples/__init__.py
pytwin/examples/downloads.py
pytwin/postprocessing/__init__.py
pytwin/postprocessing/postprocessing.py
pytwin/settings.py
pytwin/twin_runtime/TwinRuntimeSDK.dll
pytwin/twin_runtime/boost_filesystem-vc143-mt-x64-1_71.dll
pytwin/twin_runtime/hdf5-serial-1.14.5.dll
pytwin/twin_runtime/hdf5_cpp-serial-1.14.5.dll
pytwin/twin_runtime/libTwinRuntimeSDK.so
pytwin/twin_runtime/libboost_filesystem.so.1.71.0
pytwin/twin_runtime/libboost_system.so.1.71.0
pytwin/twin_runtime/libcrypto-3-x64.dll
pytwin/twin_runtime/libcrypto-anss.so.3
pytwin/twin_runtime/libhdf5-serial-1.14.5.so.310
pytwin/twin_runtime/libhdf5_cpp-serial-1.14.5.so.310
pytwin/twin_runtime/libhdf5_hl-serial-1.14.5.so.310
pytwin/twin_runtime/libhdf5_hl_cpp-serial-1.14.5.so.310
pytwin/twin_runtime/libssl-3-x64.dll
pytwin/twin_runtime/libssl-anss.so.3
pytwin/twin_runtime/libstdc++.so.6
pytwin/twin_runtime/libtwin.so
pytwin/twin_runtime/libz.so.1
pytwin/twin_runtime/licensingclient/language/de/aclext_msgs.xml
pytwin/twin_runtime/licensingclient/language/de/ansysli_msgs.xml
pytwin/twin_runtime/licensingclient/language/de/language.xml
pytwin/twin_runtime/licensingclient/language/en-us/aclext_msgs.xml
pytwin/twin_runtime/licensingclient/language/en-us/ansysli_msgs.xml
pytwin/twin_runtime/licensingclient/language/en-us/language.xml
pytwin/twin_runtime/licensingclient/language/fr/aclext_msgs.xml
pytwin/twin_runtime/licensingclient/language/fr/ansysli_msgs.xml
pytwin/twin_runtime/licensingclient/language/fr/language.xml
pytwin/twin_runtime/licensingclient/linx64/ansyscl
pytwin/twin_runtime/licensingclient/linx64/libApipWrapper.so
pytwin/twin_runtime/licensingclient/winx64/ansyscl.exe
pytwin/twin_runtime/log_level.py
pytwin/twin_runtime/msvcp140.dll
pytwin/twin_runtime/twin.dll
pytwin-0.11.0.dist-info/METADATA
pytwin-0.11.0.dist-info/WHEEL
pytwin-0.11.0.dist-info/licenses/AUTHORS
pytwin-0.11.0.dist-info/licenses/LICENSE
pytwin-0.11.0.dist-info/RECORD
