Metadata-Version: 2.4
Name: pytwin
Version: 0.11.0
Summary: A python wrapper for Ansys Digital Twin components
License: MIT
License-File: AUTHORS
License-File: LICENSE
Author: ANSYS, Inc.
Author-email: pyansys.core@ansys.com
Maintainer: ANSYS, Inc.
Maintainer-email: pyansys.core@ansys.com
Requires-Python: >=3.10,<3.14
Classifier: Development Status :: 4 - Beta
Classifier: License :: OSI Approved :: MIT License
Classifier: Operating System :: OS Independent
Classifier: Programming Language :: Python :: 3
Classifier: Programming Language :: Python :: 3.10
Classifier: Programming Language :: Python :: 3.11
Classifier: Programming Language :: Python :: 3.12
Classifier: Programming Language :: Python :: 3.13
Provides-Extra: graphics
Requires-Dist: numpy (>=1.17)
Requires-Dist: pandas (>=1.3.2)
Requires-Dist: pyvista (>=0.38.6) ; extra == "graphics"
Requires-Dist: pywin32 (>=304) ; platform_system == "Windows"
Requires-Dist: tqdm (>=4.45.0)
Project-URL: Documentation, https://twin.docs.pyansys.com/
Project-URL: Repository, https://github.com/ansys/pytwin
